phaseforgeplus/__init__.py
phaseforgeplus/io/__init__.py
phaseforgeplus/io/loaders.py
phaseforgeplus/main.py
phaseforgeplus/py.typed
phaseforgeplus/utils/__init__.py
phaseforgeplus/utils/helpers.py
phaseforgeplus/utils/objective.py
phaseforgeplus-0.1.0.dist-info/WHEEL
phaseforgeplus-0.1.0.dist-info/METADATA
phaseforgeplus-0.1.0.dist-info/RECORD
