Metadata-Version: 2.3
Name: phaseforgeplus
Version: 0.1.0
Summary: A computationally efficient, fully open-source workflow for physically-informed CALPHAD model generation and parameter fitting.
Author: Doguhan Sariturk, Courtney Kunselman, Siya Zhu, Raymundo Arroyave
Author-email: Doguhan Sariturk <dogu.sariturk@gmail.com>, Courtney Kunselman <cjkunselman18@tamu.edu>, Siya Zhu <siyazhu@tamu.edu>, Raymundo Arroyave <raymundo.arroyave@tamu.edu>
Requires-Dist: espei
Requires-Dist: notebook>=7.4.4
Requires-Dist: pycalphad>=0.11.0
Requires-Python: >=3.11
